README.txt
setup.py
defaultencodinghack/__init__.py
defaultencodinghack/configure.zcml
defaultencodinghack.egg-info/PKG-INFO
defaultencodinghack.egg-info/SOURCES.txt
defaultencodinghack.egg-info/dependency_links.txt
defaultencodinghack.egg-info/not-zip-safe
defaultencodinghack.egg-info/top_level.txt