Metadata-Version: 1.0
Name: defaultencodinghack
Version: 0.2
Summary: "Sometimes digging a hole is fast, but you will fall into it later on and pay the price" -- anonymous
Home-page: UNKNOWN
Author: Laurence Rowe
Author-email: laurence@lrowe.co.uk
License: BSD
Platform: UNKNOWN
